zdutil/cache.py
zdutil/log.py
zdutil/logging_config.ini
zdutil/utils.py
zdutil-0.0.3.dist-info/LICENSE
zdutil-0.0.3.dist-info/METADATA
zdutil-0.0.3.dist-info/WHEEL
zdutil-0.0.3.dist-info/top_level.txt
zdutil-0.0.3.dist-info/RECORD
